odoo8_addon_account_asset_management-8.0.2.6.0.99.dev70-py3.8-nspkg.pth
odoo_addons/account_asset_management/README.rst
odoo_addons/account_asset_management/__init__.py
odoo_addons/account_asset_management/__openerp__.py
odoo_addons/account_asset_management/account.py
odoo_addons/account_asset_management/account_asset.py
odoo_addons/account_asset_management/account_asset_demo.xml
odoo_addons/account_asset_management/account_asset_invoice.py
odoo_addons/account_asset_management/account_asset_invoice_view.xml
odoo_addons/account_asset_management/account_asset_view.xml
odoo_addons/account_asset_management/account_move.py
odoo_addons/account_asset_management/account_view.xml
odoo_addons/account_asset_management/res_config.py
odoo_addons/account_asset_management/res_config_view.xml
odoo_addons/account_asset_management/doc/account_asset_migration_script.txt
odoo_addons/account_asset_management/doc/changelog.rst
odoo_addons/account_asset_management/doc/index.rst
odoo_addons/account_asset_management/i18n/ab.po
odoo_addons/account_asset_management/i18n/account_asset_management.pot
odoo_addons/account_asset_management/i18n/am.po
odoo_addons/account_asset_management/i18n/ar.po
odoo_addons/account_asset_management/i18n/bg.po
odoo_addons/account_asset_management/i18n/bs.po
odoo_addons/account_asset_management/i18n/ca.po
odoo_addons/account_asset_management/i18n/ca_ES.po
odoo_addons/account_asset_management/i18n/cs.po
odoo_addons/account_asset_management/i18n/da.po
odoo_addons/account_asset_management/i18n/de.po
odoo_addons/account_asset_management/i18n/el_GR.po
odoo_addons/account_asset_management/i18n/en_AU.po
odoo_addons/account_asset_management/i18n/en_GB.po
odoo_addons/account_asset_management/i18n/es.po
odoo_addons/account_asset_management/i18n/es_AR.po
odoo_addons/account_asset_management/i18n/es_CL.po
odoo_addons/account_asset_management/i18n/es_CO.po
odoo_addons/account_asset_management/i18n/es_CR.po
odoo_addons/account_asset_management/i18n/es_DO.po
odoo8_addon_account_asset_management-8.0.2.6.0.99.dev70.dist-info/METADATA
odoo8_addon_account_asset_management-8.0.2.6.0.99.dev70.dist-info/WHEEL
odoo8_addon_account_asset_management-8.0.2.6.0.99.dev70.dist-info/namespace_packages.txt
odoo8_addon_account_asset_management-8.0.2.6.0.99.dev70.dist-info/top_level.txt
odoo8_addon_account_asset_management-8.0.2.6.0.99.dev70.dist-info/RECORD
