Metadata-Version: 2.1
Name: odoo8-addon-account-asset-management
Version: 8.0.2.6.0.99.dev70
Summary: Assets Management
Home-page: http://www.noviat.com
Author: OpenERP & Noviat,Odoo Community Association (OCA)
Author-email: support@odoo-community.org
License: AGPL-3
Platform: UNKNOWN
Classifier: Programming Language :: Python
Classifier: Framework :: Odoo
Classifier: Framework :: Odoo :: 8.0
Classifier: License :: OSI Approved :: GNU Affero General Public License v3
Requires-Python: ~=2.7
Requires-Dist: odoo (<9.0a,>=8.0a)
